ACKNOWLEDGEMENTS
AUTHORS
LICENSE
MANIFEST.in
README
dependencies.ini
run_tests.py
setup.cfg
setup.py
scripts/knownfolders.py
tests/__init__.py
tests/appcompatcache.py
tests/filters.py
tests/hexdump.py
tests/interface.py
tests/knownfolders.py
tests/msie_zone_info.py
tests/output_writer.py
tests/profiles.py
tests/programscache.py
tests/sam.py
tests/services.py
tests/shellfolders.py
tests/sysinfo.py
tests/task_cache.py
tests/test_lib.py
tests/type_libraries.py
tests/userassist.py
utils/dependencies.py
winregrc/__init__.py
winregrc/appcompatcache.py
winregrc/collector.py
winregrc/dfvfs_pyregf.py
winregrc/errors.py
winregrc/filters.py
winregrc/hexdump.py
winregrc/interface.py
winregrc/knownfolders.py
winregrc/msie_zone_info.py
winregrc/output_writer.py
winregrc/profiles.py
winregrc/programscache.py
winregrc/sam.py
winregrc/services.py
winregrc/shellfolders.py
winregrc/sysinfo.py
winregrc/task_cache.py
winregrc/type_libraries.py
winregrc/userassist.py
winregrc.egg-info/PKG-INFO
winregrc.egg-info/SOURCES.txt
winregrc.egg-info/dependency_links.txt
winregrc.egg-info/top_level.txt