Metadata-Version: 1.1
Name: winregrc
Version: 20170525
Summary: Windows Registry resources (winregrc).
Home-page: https://github.com/libyal/winreg-kb
Author: Joachim Metz
Author-email: joachim.metz@gmail.com
License: Apache License, Version 2.0
Platform: UNKNOWN
Classifier: Development Status :: 3 - Alpha
Classifier: Environment :: Console
Classifier: Operating System :: OS Independent
Classifier: Programming Language :: Python
